compas_python_utils/__init__.py
compas_python_utils/_version.py
compas_python_utils/h5copy.py
compas_python_utils/h5sample.py
compas_python_utils/h5view.py
compas_python_utils/cosmic_integration/ClassCOMPAS.py
compas_python_utils/cosmic_integration/ClassCosmicIntegrator.py
compas_python_utils/cosmic_integration/ClassMSSFR.py
compas_python_utils/cosmic_integration/FastCosmicIntegration.py
compas_python_utils/cosmic_integration/SNR_Grid_IMRPhenomPv2_FD_all_noise.hdf5
compas_python_utils/cosmic_integration/__init__.py
compas_python_utils/cosmic_integration/cosmology.py
compas_python_utils/cosmic_integration/generate_frame_file.py
compas_python_utils/cosmic_integration/selection_effects.py
compas_python_utils/cosmic_integration/totalMassEvolvedPerZ.py
compas_python_utils/cosmic_integration/binned_cosmic_integrator/__init__.py
compas_python_utils/cosmic_integration/binned_cosmic_integrator/bbh_population.py
compas_python_utils/cosmic_integration/binned_cosmic_integrator/bin_2d_data.py
compas_python_utils/cosmic_integration/binned_cosmic_integrator/conversions.py
compas_python_utils/cosmic_integration/binned_cosmic_integrator/cosmological_model.py
compas_python_utils/cosmic_integration/binned_cosmic_integrator/detection_matrix.py
compas_python_utils/cosmic_integration/binned_cosmic_integrator/detection_rate_computer.py
compas_python_utils/cosmic_integration/binned_cosmic_integrator/gpu_utils.py
compas_python_utils/cosmic_integration/binned_cosmic_integrator/io.py
compas_python_utils/cosmic_integration/binned_cosmic_integrator/plotting.py
compas_python_utils/cosmic_integration/binned_cosmic_integrator/snr_grid.py
compas_python_utils/detailed_evolution_plotter/__init__.py
compas_python_utils/detailed_evolution_plotter/plot_detailed_evolution.py
compas_python_utils/detailed_evolution_plotter/van_den_heuvel_figures/1.png
compas_python_utils/detailed_evolution_plotter/van_den_heuvel_figures/10.png
compas_python_utils/detailed_evolution_plotter/van_den_heuvel_figures/11.png
compas_python_utils-0.0.2.dist-info/METADATA
compas_python_utils-0.0.2.dist-info/WHEEL
compas_python_utils-0.0.2.dist-info/entry_points.txt
compas_python_utils-0.0.2.dist-info/top_level.txt
compas_python_utils-0.0.2.dist-info/RECORD
