Metadata-Version: 2.1
Name: compas_python_utils
Version: 0.0.2
Summary: COMPAS Python Utilities
Author-email: COMPAS Team <compas-dev@googlegroups.com>
Project-URL: Homepage, https://github.com/TEAMCompas/COMPAS
Project-URL: Bug Reports, https://github.com/TEAMCompas/COMPAS/issues
Project-URL: Source, https://github.com/TEAMCompas/COMPAS
Classifier: Development Status :: 5 - Production/Stable
Classifier: Intended Audience :: Developers
Classifier: Intended Audience :: Science/Research
Classifier: License :: OSI Approved :: MIT License
Classifier: Operating System :: OS Independent
Classifier: Programming Language :: Python
Classifier: Programming Language :: Python :: 3
Requires-Python: >=3.8
Requires-Dist: numpy>=1.16
Requires-Dist: h5py
Requires-Dist: argparse
Requires-Dist: stroopwafel
Requires-Dist: pytest>=3.6
Requires-Dist: pre-commit
Requires-Dist: flake8
Requires-Dist: black==22.10.0
Requires-Dist: isort
Requires-Dist: matplotlib>=3.3.2
Requires-Dist: pandas
Requires-Dist: astropy>=4.0
Requires-Dist: scipy>=1.5.0
Requires-Dist: latex
Requires-Dist: PyYAML
Requires-Dist: tqdm
Requires-Dist: corner
Provides-Extra: docs
Requires-Dist: sphinx>=7.0.1; extra == "docs"
Requires-Dist: numpydoc; extra == "docs"
Requires-Dist: nbsphinx; extra == "docs"
Requires-Dist: sphinx_rtd_theme>=1.2.2; extra == "docs"
Requires-Dist: sphinx-tabs; extra == "docs"
Requires-Dist: sphinx-argparse; extra == "docs"
Requires-Dist: sphinx-math-dollar>=1.2; extra == "docs"
Requires-Dist: sphinxcontrib.bibtex; extra == "docs"
Requires-Dist: linuxdoc; extra == "docs"
Requires-Dist: ipython; extra == "docs"
Requires-Dist: readthedocs-sphinx-search>=0.1.1b; extra == "docs"
Requires-Dist: sphinx-togglebutton; extra == "docs"
Requires-Dist: linuxdoc>=20210324; extra == "docs"
Provides-Extra: dev
Requires-Dist: pytest-cov; extra == "dev"
Requires-Dist: pre-commit; extra == "dev"
Requires-Dist: flake8; extra == "dev"
Requires-Dist: black==22.10.0; extra == "dev"
Requires-Dist: isort; extra == "dev"
Requires-Dist: coverage-badge; extra == "dev"
Requires-Dist: deepdiff; extra == "dev"
Requires-Dist: jupytext; extra == "dev"
Requires-Dist: jupyter-autotime; extra == "dev"
Requires-Dist: memory_profiler; extra == "dev"
Requires-Dist: nbconvert; extra == "dev"
Requires-Dist: ipykernel; extra == "dev"
Provides-Extra: gpu
Requires-Dist: cupy; extra == "gpu"
